[
  {
    "message": "永遠「はぁっ！　んんっ……ああっ、んんっ！　んあぁ！」"
  },
  {
    "message": "ガチガチに怒張したペニスで蜜壷を激しく突き上げる動きに合わせ、永遠は妖艶に腰を振り肢体を蠢かせていく。"
  },
  {
    "message": "永遠「あふぅ！　はぁん！　……あっ、あふぅ！　はあっ、はぁん！」"
  },
  {
    "message": "永遠「……大樹さんの硬いオチンポで……薄汚れたおまんこ……激しく突いて……んあぁぁ！」"
  },
  {
    "message": "大樹「ずいぶん奴等に中出しされたんですね……永遠さんの膣を肉棒で擦るたびにどんどんあふれ出てきますよ……」"
  },
  {
    "message": "永遠「んっ！　は、はい……ごめんなさい……大樹さん……今日も沢山オマンコに、精液を出されてしまいました……」"
  },
  {
    "message": "永遠「……かき出さないと……大樹さんのオチンチンで……いっぱいオマンコを擦って……綺麗にしないと……」"
  },
  {
    "message": "永遠「その後で……ください……大樹さんの精液……中に出して……汚らわしいモノを全て洗い流して……」"
  },
  {
    "message": "俺が不貞を詰り彼女が許しを請う……"
  },
  {
    "message": "いつのまにか、嫉妬と背徳感でお互いの興奮を高め合うやり方が、俺達の愛し合う形として定着していた。"
  },
  {
    "message": "大樹「そんな事言って、ただオマンコを擦って欲しいだけなんじゃないんですか？」"
  },
  {
    "message": "永遠「あっ……ああぁぁ……ちっ、違います……」"
  },
  {
    "message": "大樹「本当は……もう俺なんかどうでもよくて……膣に精液を流し込まれさえすれば、誰のペニスでもいいんじゃないんですか？」"
  },
  {
    "message": "永遠「んんっ！　ち、違う……はぁ、ああっ……そんな事無い……」"
  },
  {
    "message": "永遠「……大樹さん……信じて……本当は私……貴方以外には……指も触れられたくないんです……」"
  },
  {
    "message": "大樹「嘘をつかないでくださいよ……さっき二人きりで今朝までまぐわっていた太っちょの禿オヤジ……あいつと随分濃厚なセックスをしていましたよね……」"
  },
  {
    "message": "永遠「……ああぁぁ……は、はい……しました……」"
  },
  {
    "message": "大樹「あの男とシている時は……他の奴等に比べ明らかに乱れてました……」"
  },
  {
    "message": "大樹「もしかして……あのキモオヤジ……永遠さんのお気に入りなんですか？」"
  },
  {
    "message": "俺の詰問を受け、先ほどまで犯されていた男との行為を思い出したのだろう……"
  },
  {
    "message": "永遠はギュッギュッと蜜壷を収縮させ、今現在差し込まれている俺のペニスを強く締め付けてきた。"
  },
  {
    "message": "永遠「……は、はいぃぃ……す、凄い……あの人……凄いんです……」"
  },
  {
    "message": "大樹「どんな風に凄いんですか？」"
  },
  {
    "message": "永遠「あの大きな体格で私の上に覆いかぶさって……ほんの少しですら動けなくさせた後……太いペニスを無理やりオマンコに入れてくるんです……」"
  },
  {
    "message": "永遠「大樹さんと違って……オチンチンは先が酷く曲がっていて……オマンコで動かすと亀頭がしつこいぐらい壁を擦るんです……」"
  },
  {
    "message": "永遠「側位ですると、突く度に丁度子宮口にオチンチンの先が差し込まれて……」"
  },
  {
    "message": "永遠「子宮を苛められたくないならと、私に舌を突き出すように命令してキスを強要し……」"
  },
  {
    "message": "永遠「舌と舌をねっとりと絡めながら……結局約束を守らず、執拗に、執拗に子宮口を突いてくるんです……」"
  },
  {
    "message": "永遠「……私……何度も果てさせられて……気を失ってもペニスで突いて起こされて……」"
  },
  {
    "message": "永遠「オチンポ抜かないまま……数え切れないぐらい中に出されました……」"
  },
  {
    "message": "大樹「……それで、全部で何回イッたんですか？」"
  },
  {
    "message": "永遠「お、覚えていません……よくわからなくなるぐらい……イキました……」"
  },
  {
    "message": "大樹「俺とする時よりも凄い声だしてましたし、派手にイッてましたよ……」"
  },
  {
    "message": "大樹「凄く幸せそうでした……何度も果てて満たされた気持ちになったんじゃないんですか？」"
  },
  {
    "message": "永遠「……はひぃ……そう……何度もイッて……気持ちよくて……凄く……満たされました……」"
  },
  {
    "message": "大樹「じゃあ……アイツとしている時は……邪魔しないように目を瞑って居た方がいいですかね……」"
  },
  {
    "message": "永遠「だ、駄目……大樹さんが見ていないと駄目……」"
  },
  {
    "message": "大樹「どうして？　気持ちいいのは俺のペニスじゃないんですよね？」"
  },
  {
    "message": "永遠「違う……しているのを……大樹さんに見られるのが……いいんです……ただ犯されるより……凄く興奮する……」"
  },
  {
    "message": "大樹「……見てるだけでいいんですか？　オチンチンは必要ない？」"
  },
  {
    "message": "永遠「い、要ります！」"
  },
  {
    "message": "永遠「……あの人に犯されて乱れている時に……私、あとで大樹さんに叱られながらすると思って、抱かれる事以上に興奮していました……」"
  },
  {
    "message": "大樹「……あいつに抱かれながら……俺のチンポを欲していたんですね……」"
  },
  {
    "message": "永遠「はい……コレが欲しかった……大樹さんのオチンチンが欲しかったんです……」"
  },
  {
    "message": "言葉以上の想いを伝えようと、永遠は膣内をキュッと締め付け、肉棒全体をしっかりと包み込んでみせる。"
  },
  {
    "message": "永遠「好きでもない男に犯され……いやらしく乱れた私の姿を見せて……」"
  },
  {
    "message": "永遠「……それを見て興奮した大樹さんに、沢山犯されたかったんです……」"
  },
  {
    "message": "大樹「……凄く……凄く興奮しましたよ……永遠さん……悔しいぐらい乱れてたし……」"
  },
  {
    "message": "永遠「で、でも……ふぅ、はぁ……わ、私……」"
  },
  {
    "message": "永遠「……わ、私は……っく……い、今の方が興奮しています……」"
  },
  {
    "message": "その興奮を形にした永遠の面持ちは昔の清楚さは欠片も無く、性獣と呼ぶのが相応しいような有様へとその顔つきを変化させている。"
  },
  {
    "message": "永遠「アノ人に犯されていた時に感じていた快感が……今大樹さんから与えられている快感と重なっているんです……」"
  },
  {
    "message": "永遠「……このまま乱暴に突かれたら……きっと私……正気じゃいられなくなる……」"
  },
  {
    "message": "大樹「それは……正気を失うぐらい、乱暴に犯して欲しいって事ですか？」"
  },
  {
    "message": "永遠「違う……しないで……ゆっくり……じっくりと貴方を感じさせて」"
  },
  {
    "message": "大樹「また、いい所で奴らが来て……あいつらにイかされてしまうかもしれませんよ？」"
  },
  {
    "message": "永遠「それでもかまわない……そうして……また大樹さんに責められたい……」"
  },
  {
    "message": "永遠「乱暴に子宮を突かれて……頭を空っぽにさせられて、何もかも忘れたい……もっともっと長く感じていたい……」"
  },
  {
    "message": "大樹「いやらしいですね……そんなにセックスが好きなんですか？」"
  },
  {
    "message": "永遠「ち、ちがう……」"
  },
  {
    "message": "永遠「私が感じたいのは……」"
  },
  {
    "message": "永遠「……貴方よ……大樹さん……」"
  },
  {
    "message": "大樹「……永遠……さん……」"
  },
  {
    "message": "永遠「貴方が好き……好きで好きで堪らないの……」"
  },
  {
    "message": "永遠「……この気持ちを壊されたくない……だから激しく犯さないで……お願い……」"
  },
  {
    "message": "俺はコクリと頷くと、肉棒をゆっくりと深く大きく動かす形で、永遠の強い願いに応えてやる事にした。"
  },
  {
    "message": "永遠「あっ、ああっ、ああ！　……大樹さん……いい……気持ちいいです……」"
  },
  {
    "message": "永遠「このまま、突いて……ふぅ、んっ……私を、罵って……」"
  },
  {
    "message": "大樹「……俺のことが好きだっていうクセに……」"
  },
  {
    "message": "大樹「その俺の前で、別の男に抱かれて……気持ちよさそうにヨガるなんて、永遠さんは酷いです……」"
  },
  {
    "message": "永遠「ああっ……ごめんなさい……犯されてるのに……果てながら……膣に精液欲しいって……お願いしてごめんなさい……」"
  },
  {
    "message": "大樹「……俺の子を宿してもいないのに子宮に中出しされまくって……もう俺以外の子供、出来ちゃってるんじゃないんですか？」"
  },
  {
    "message": "永遠「……ああっ……ご、ごめんなさい……私、きっとあの人達の子を妊娠してます……約束やぶって……大樹さん以外の子を宿してごめんなさい……」"
  },
  {
    "message": "大樹「……俺のペニスより……あいつ等の方が気持ちいいって、何度も何度も言いましたね……」"
  },
  {
    "message": "永遠「……い、言いました……大樹さんの前で、貴方のチンポより他のほうが全然いいって……」"
  },
  {
    "message": "永遠「縛られた大樹さんの前で、告白させられて……」"
  },
  {
    "message": "永遠「そのまま絶頂して、漏らしたおしっこを貴方の顔にかけてしまいました……」"
  },
  {
    "message": "永遠「んんっ！　そ、それから……大樹さん以外では感じられなかったお尻の穴も、今では立派なケツマンコとしてペニス入れまくりです……」"
  },
  {
    "message": "永遠「そして……お、お腹の中に……今も沢山の精液を溜め込んで、出さないよう命じられているんです……」"
  },
  {
    "message": "大樹「……本当に、酷い人ですね……永遠さんって……」"
  },
  {
    "message": "永遠「で、でも……ああっ！　そ、それでも大樹さんが好き……好きなんです！　……はあぁ……ああっ！」"
  },
  {
    "message": "大樹「俺も……っく、どんなに汚されても……永遠さんが好きです……」"
  },
  {
    "message": "永遠「ああっ！　……う、嬉しい！　……大樹さん……大樹さん……」"
  },
  {
    "message": "永遠「はぁっ、ああっ……感じ、させて……大樹さんを……もっと……もっとぉ！」"
  },
  {
    "message": "大樹「感じたいなら……もっとほら……がっついて腰を振ってください！」"
  },
  {
    "message": "永遠「は、はいぃ！　……はあっ、はぁん！　あっ、ああっ！　いいっ！　大樹さんのおちんぽ……いいっ……いいのぉ……」"
  },
  {
    "message": "永遠「はあんっ、んあっ……長いストロークの中……膣のお肉がかき回されて……はぅん、んんっ……的確に、私の弱い所を擦っていく……」"
  },
  {
    "message": "永遠「ふぅ、はぁ……大樹さんの愛しいおちんぽ……あの人達より少しだけ細くて短い……愛しいおちんぽ……」"
  },
  {
    "message": "永遠「けどあの人達より大樹さんの方が硬い……それに凄くカリ高なのが……いいっ、いいんですっ！　はぁっ！　感じるうぅ！」"
  },
  {
    "message": "永遠「はあっ！　あぁん！　もっと、もっとぉ！　大樹さんを、大樹さんの感触を！　私に強く刻み込んでぇ！」"
  },
  {
    "message": "大樹「……ふふ……そんな俺の事を強く感じたいなら……あとは中出ししかありませんね！」"
  },
  {
    "message": "永遠「はあぁ……あふぅっ……そう、中出し……大樹さんのザーメン……はあぁん……」"
  },
  {
    "message": "永遠「はあっ、あふぅ……穢れたオマンコにぃ……大樹さんの愛を……流し、込んでぇ……お願いぃ……」"
  },
  {
    "message": "大樹「ならその前に、もっともっと気持ちよくならないと……」"
  },
  {
    "message": "永遠「はあぁ……もっと……んんっ、んはぁ……もっと気持ちよく……」"
  },
  {
    "message": "大樹「そうです……あいつらのペニスを忘れるぐらい……激しく子宮口と俺のペニスをぶつけ合いましょう！」"
  },
  {
    "message": "永遠「は、はいっ！　わかりました大樹さん！」"
  },
  {
    "message": "永遠「んぐっ、んはぁ……あっ、はあっ、はあっ！　……あくっ、あっ、あはぁん……」"
  },
  {
    "message": "永遠「大樹さん……種付けされたくて降りてきた子宮に、大樹さんのおちんちんがぶつかるぅ……おまんこ疼くぅ……はあっ、はあぁん……」"
  },
  {
    "message": "大樹「はあっ、はあっ！　……永遠さん……永遠さん！」"
  },
  {
    "message": "永遠「いいっ、いいですぅ……大樹さん……おまんこ突いて……大樹さんで私を埋め尽くして……」"
  },
  {
    "message": "永遠「はあぁん……幸せぇ……こうして大樹さんとセックスしているだけで……幸せすぎて……頭が真っ白になって……何も考えられなくなるぅ……」"
  },
  {
    "message": "永遠「……家の事も……家族の事も……大樹さんのオチンポ以外……何もかも……全てが色あせていくぅ……」"
  },
  {
    "message": "大樹「んぐっ……永遠さん……俺……もう……いくっ、いきますぅ！」"
  },
  {
    "message": "永遠「はあっ、待って大樹さん！　私ももう少し……くる……きてるぅ……大樹さんの愛しいオチンチンで……いくっ……熱いの……くるぅう！」"
  },
  {
    "message": "永遠「はぁ！　はあぁんっ！　きました……ああっ！　大樹さん！　私も、もうイキます！」"
  },
  {
    "message": "永遠「はあっ！　大樹さん！　イキます！　イキます！　まんこ！　おまんこイキますぅ！」"
  },
  {
    "message": "永遠「ああっ！　んんぉぉお！　……い、イク、イクッ、イクッ！　イクゥゥゥ！」"
  },
  {
    "message": "奥へと強く打ち付けた亀頭を逃がすまいと痙攣するように膣が締まり、ヒダがざわめくように肉棒全体を撫で回していく……"
  },
  {
    "message": "その甘美な蜜壷の刺激に耐え切れず、俺は込み上げた欲望を永遠が求めるままに解き放った。"
  },
  {
    "message": "永遠「ひぐっ！？　んあっ！　んおぉ！！　んんんぉぉぉおおおおお！！！」"
  },
  {
    "message": "永遠「んあぁ！　はぁ！　ふぅ！　……はぁっ、奥に……大樹さんの精液……凄い……で、出てる！」"
  },
  {
    "message": "永遠が俺とまぐわう事を願っていたように……"
  },
  {
    "message": "俺は痴態を見せ付けられ我慢していた分に自らの想いを上乗せして、大量の精液をドクドクと膣内に流し込んでいく。"
  },
  {
    "message": "愛する者の吐精を受けた永遠は熱い吐息を漏らしながら、じっと至福の感覚を味わい続ける。"
  },
  {
    "message": "永遠「ああっ……溢れる……他のザーメン流れ出て……大樹さんの綺麗な精液で……満たされる……穢れた子宮が綺麗になる……」"
  },
  {
    "message": "永遠「はあっ、はあっ……んはぁ……ああっ……幸せぇ……大樹さん……私……幸せです……」"
  },
  {
    "message": "大樹「俺もです……永遠さんの傍に居られて……永遠さんとセックスできて……凄く幸せです」"
  },
  {
    "message": "永遠「んあっ……あんなに出したのに……大樹さんのおちんちん……また硬くなってきたわ……素敵……」"
  }
]