[
  {
    "message": "大樹（何が……）"
  },
  {
    "message": "大樹（……何が……お前のものだ！！）"
  },
  {
    "message": "縛られ痛めつけられた身体では、伊丹を止めるのは無理だろう……"
  },
  {
    "message": "ならば……この自由に動く口先だけでも……ヤツに抗い続けてやる……"
  },
  {
    "message": "大樹「紫衣の言う通りだ……お前の物なんか、何一つねぇんだよ……」"
  },
  {
    "message": "伊丹「へぇ……」"
  },
  {
    "message": "大樹「てめぇみたいなクズには、この家なんかより……豚箱あたりが、お似合いに決まってんだよ……」"
  },
  {
    "message": "伊丹「……随分と威勢がいい事を言うじゃねぇか……橋詰」"
  },
  {
    "message": "金庫からこちらへやってきた伊丹は、靴底で俺の額をグリグリと踏みつけ始めた。"
  },
  {
    "message": "大樹「っ……」"
  },
  {
    "message": "伊丹「なあ、橋詰……俺が全て手に入れられたのも、お前のおかげだ……少しだけだが、感謝してやるよ」"
  },
  {
    "message": "感謝の気持ちを込めているつもりなのか、徐々に踏みつける力が強まっている気がする。"
  },
  {
    "message": "押しつぶされる恐怖を跳ね除け、俺は伊丹を射殺すように睨みつけてやった。"
  },
  {
    "message": "伊丹「心が広い俺様は、お前が今まで俺を恨み生意気な事を考えていた事だって許してやる……」"
  },
  {
    "message": "永遠「も、もうやめて、貴方！」"
  },
  {
    "message": "紫衣「その薄汚い足を、大樹から離しなさい！」"
  },
  {
    "message": "伊丹「だがな……実際に俺を裏切っちまうのはアウトだ……それに、俺の許しもなく紫衣へ手を出してるってのも気にいらねぇ……」"
  },
  {
    "message": "大樹「だったら……何だって言うんだよ……」"
  },
  {
    "message": "伊丹「……何よりムカつくのは……床でこうして踏まれるのがお似合いのゴミのくせに……まだ諦めねぇぞって目が、気にいらねぇなぁ！」"
  },
  {
    "message": "伊丹は押し当てていた足を持ち上げると、空缶を潰すかの如くガシガシと俺の頭を踏みつけていく。"
  },
  {
    "message": "大樹「んぐっ……あぐっ……があぁ！　……くうっ！」"
  },
  {
    "message": "避けようと頭を振っても、何発かは避け切れずに食らってしまう。"
  },
  {
    "message": "それでも……こうして俺が抗い続ければ……"
  },
  {
    "message": "ヤツの次の目的である姉妹のレイプに、待ったをかけ続ける事が出来る……"
  },
  {
    "message": "大樹（ぐっ……くそっ！　……ま、まだ……まだだ……）"
  },
  {
    "message": "大樹（何もかもてめぇの思い通りにさせるもんか……諦めて……たまるかよ！）"
  },
  {
    "message": "伊丹「……ふん……往生際の悪いヤツだなぁ……お前は……」"
  },
  {
    "message": "伊丹「女達の前に……お前を少し躾けてやるとするか……」"
  },
  {
    "message": "額に押し付けられていた靴底が、喉元へと移動していく……"
  },
  {
    "message": "手足を縛られ逃げようもない俺には……伊丹の体重を首で受けるしかない。"
  },
  {
    "message": "ジワジワとヤツの体重が足に乗り、無防備な喉が圧迫されていく。"
  },
  {
    "message": "大樹「がはっ！　がぁ！　があぁあああぁ！！」"
  },
  {
    "message": "伊丹「なぁに……殺しやしねぇよ……安心しな、俺はこういうのになれているからな……」"
  },
  {
    "message": "伊丹「薬もたっぷり使って……苦しんで、苦しんで……それでも死ねない……苦痛の中にある快楽をお前に味わわせてやる……」"
  },
  {
    "message": "伊丹「……何でも言う事を聞く……人に蔑まれ、快感を得る変態野郎に……しっかり躾けなおしてやるからな……」"
  },
  {
    "message": "大樹（し、しぬ……あぁ……あ……ぁ……ぁ）"
  },
  {
    "message": "伊丹「……今日から……この金庫が……お前の住処だ……」"
  },
  {
    "message": "額を蹴られた時に切れて出血した血が目に入ったのか、赤く滲んだ視界が白くぼやけ始めていく……"
  },
  {
    "message": "次第に朦朧とする意識……"
  },
  {
    "message": "女達の悲鳴や懇願が遠くから聞こえる……"
  },
  {
    "message": "……そんな中……"
  },
  {
    "message": "誰かの携帯の着信音らしきメロディが、俺の鼓膜を震わせていく……"
  },
  {
    "message": "大樹（……何で携帯の音が……）"
  },
  {
    "message": "大樹（伊丹が中継器を壊して……）"
  },
  {
    "message": "大樹（携帯に……電波が……届くはず…………ない……のに…………）"
  },
  {
    "message": "聞こえるはずのない電子音の幻聴を聞きながら……"
  },
  {
    "message": "俺の意識は暗闇の沼へ引き込まれるように……ずぶずぶと落ちていった……"
  },
  {
    "message": "・\r\n"
  },
  {
    "message": "・\r\n"
  },
  {
    "message": "・"
  },
  {
    "message": "暗闇へ光が射すかのように、唐突に圧迫されていた気道が確保され、新鮮な空気が肺に流れ込んでいく。"
  },
  {
    "message": "大樹「んはぁ！　ひぃ、はぁ、ひぃ……はあぁ……」"
  },
  {
    "message": "大樹（な、何だ！？　……た、たすかった……のか？）"
  },
  {
    "message": "ホッとしたものの、何が起きたのか把握しなければ安心は出来ない。"
  },
  {
    "message": "いまだボヤけている視界の中……"
  },
  {
    "message": "俺は自分の首を踏みつけていた伊丹の姿を、必死に探し始めた。"
  },
  {
    "message": "……どうやら……伊丹の野郎は、仰向けのまま身動きもせず金庫の中に納まっているようだ。"
  },
  {
    "message": "何が起きたのかは分からない……"
  },
  {
    "message": "……自分の身も、姉妹の身も安全が確保されたかどうか怪しい所。"
  },
  {
    "message": "それでも伊丹にとって宜しくない出来事が起きたのは……間違いなさそうだ。"
  },
  {
    "message": "大樹「……げほっ……ざまぁ……げほっ……げほっ……」"
  },
  {
    "message": "微かに残った力を振り絞り、悪態を声に出すと……再び意識は闇の中へと引きずり込まれていく。"
  },
  {
    "message": "徐々に暗くなる視界の中……"
  },
  {
    "message": "杏里の無事な姿が視界の端に映った所で……俺の意識は、幕を閉じた……"
  },
  {
    "message": "・\r\n"
  },
  {
    "message": "・\r\n"
  },
  {
    "message": "・"
  },
  {
    "message": "大樹（……うぅ……）"
  },
  {
    "message": "大樹「し、紫衣？　……げほっ……げほっ……」"
  },
  {
    "message": "喉を圧迫されていたせいか、かすれた酷い声が口からこぼれ出る。"
  },
  {
    "message": "床に倒れていたはずが、後頭部が柔らかく暖かい……"
  },
  {
    "message": "その温もりが一番傍にいる彼女の膝枕だと気づき……俺の胸に、暖かな安らぎがじんわりと広がっていく。"
  },
  {
    "message": "紫衣「大丈夫？　大樹」"
  },
  {
    "message": "大樹「あ、ああ……」"
  },
  {
    "message": "大樹「そ、そうだ、伊丹は？」"
  },
  {
    "message": "気絶する直前に見た時は金庫の中にいたが……今はその姿がどこにも見当たらない。"
  },
  {
    "message": "杏里「ともくんより重症だったので、警察がお母様と一緒に先に病院へ搬送していきました」"
  },
  {
    "message": "大樹「そ、そうか……」"
  },
  {
    "message": "身動きせずとも全身がズキズキと痛み、身体を動かす気持ちを萎えさせていく。"
  },
  {
    "message": "何度も気絶するほど痛めつけられ、こちらも満身創痍だと思うのだが……"
  },
  {
    "message": "そんな俺以上に、伊丹は酷い怪我を負ったというのだろうか？"
  },
  {
    "message": "大樹（……気絶してる間に、何があったんだ？）"
  },
  {
    "message": "綺羅「おにいちゃん、大丈夫？」"
  },
  {
    "message": "大樹「綺羅……お前、船着場から逃げた後、大丈夫だったのか？」"
  },
  {
    "message": "綺羅「うん、危ない所をおねえちゃんが助けてくれたよ」"
  },
  {
    "message": "大樹「……そうか……そういえば、杏里……お前は何処で何していたんだ？」"
  },
  {
    "message": "杏里「えっとですね……綺羅と一緒に寝ようと思って部屋で待っていたら、何時までたっても帰ってこないので……心配になって、外へ探しに出たんです」"
  },
  {
    "message": "杏里「そうしたら悲鳴が聞こえて、そこへ急いで向かうと綺羅が襲われていたので……近くのものをポイッと投げつけて気絶させました」"
  },
  {
    "message": "綺羅「……飛んできたシロモノは……その擬音に相応しくない質量だったけどね……」"
  },
  {
    "message": "大樹（……何を飛ばしたんだよ……）"
  },
  {
    "message": "杏里「その後、外部に連絡して……」"
  },
  {
    "message": "大樹「外部に連絡？　……電話は、使えなかったはずだけど……」"
  },
  {
    "message": "ふと、伊丹が中継器を潰し外部との連絡を遮断した事を自慢げに説明した時の状況が脳裏に浮かんでいく。"
  },
  {
    "message": "杏里「はい、電波が飛んでなくて圏外状態でしたね」"
  },
  {
    "message": "杏里「なので中継器の状態を確認し、抜けているプラグを適当に差し込んで使えるようにしたんです」"
  },
  {
    "message": "大樹「…………………………」"
  },
  {
    "message": "大樹「あ、あれ……こ、壊れてたんじゃないの？」"
  },
  {
    "message": "杏里「はい、恐らく今回の事を外部へ漏らさぬよう一時的な手段として、プラグを引き抜いたんだと思います」"
  },
  {
    "message": "大樹（つまりあの時、壊したと言ったのは……）"
  },
  {
    "message": "大樹（俺の抗う力を失わせる為の方便だった……という事か……）"
  },
  {
    "message": "てっきり素人には修復不能なまでに破壊されてしまったと思い込んでいたが……"
  },
  {
    "message": "確かに今後の事を考えたら、自力で修理可能な状態にするに決まっている。"
  },
  {
    "message": "相手のブラフを何一つ疑いもせず完璧に信じていた自分が……あまりにも情けない。"
  },
  {
    "message": "杏里「警察が電話で島へ駆けつけた後は、道中色々あってここへ来たわけですが……少々遅くなってすみませんでした」"
  },
  {
    "message": "綺羅「……おねえちゃん……途中の説明、えらい端折ったね……まぁ、いいけど……」"
  },
  {
    "message": "大樹「道中何があったのかは、あとで聞くとして……」"
  },
  {
    "message": "大樹「つまり俺は伊丹との騙し合いに負けて、ボコられただけで……」"
  },
  {
    "message": "大樹「何の役にも立たなかったって事か……はは……ははは……」"
  },
  {
    "message": "伊丹と再会し、ヤツに復讐を誓ってずっと頑張ってきたというのに……"
  },
  {
    "message": "いきがるだけで何一つ伊丹に力及ばず、一矢報いる事すら出来なかった。"
  },
  {
    "message": "大樹（……ホント……情けないにもホドがあるな……）"
  },
  {
    "message": "紫衣「何を言ってるの……作戦はザルだったけど、伊丹の注意を引き付けたからこそ杏里が動けたんじゃない……見事な囮役だったわ」"
  },
  {
    "message": "大樹「戦略的には重要ですよね！　ど、どうも！」"
  },
  {
    "message": "杏里「私の策では、やっぱり逃げられていたと思いますし……ともくんの油断させて逃げ場をなくす作戦が成功したんです」"
  },
  {
    "message": "紫衣「それにお母様だって取り戻せたわ……貴方のお蔭よ」"
  },
  {
    "message": "綺羅「頑張ったねお兄ちゃん、えらいえらい」"
  },
  {
    "message": "大樹「そっかぁ……へへ……そうだよな……え、えへん！」"
  },
  {
    "message": "周りから執拗にヨイショされ、身体中の痛みすら何か勲章のように思え自然に笑みが浮かび上がる。"
  },
  {
    "message": "調子がいいと笑い始めた姉妹達に合わせ……"
  },
  {
    "message": "俺も痛みに少しばかり顔を歪ませつつ、仲良く笑い声をあげるのであった……"
  },
  {
    "message": "・\r\n"
  },
  {
    "message": "・\r\n"
  },
  {
    "message": "・"
  },
  {
    "message": "姉妹達に囲まれ紫衣の膝枕を堪能していた所、警察が現れ署へ同行して欲しいと言われ……"
  },
  {
    "message": "俺と紫衣は姉妹達を残し、警察の船に乗り込む事となった……"
  },
  {
    "message": "大樹「さっきからくっつきすぎだろ……俺達の関係が噂になっちまうぞ」"
  },
  {
    "message": "紫衣「いいじゃない、噂が広がったって……どうせすぐ結婚するんだし」"
  },
  {
    "message": "紫衣「それに気を張りすぎて少し疲れたのよ……いいでしょ、少しぐらい」"
  },
  {
    "message": "大樹「むしろ寄りかかりたいのは俺のほうだぞ……今も痛いし、もうこの場で寝たいぐらいだ……」"
  },
  {
    "message": "紫衣「貴方も寄りかかっていいわよ……それともそんなに私に寄りかかられるのがいやなの？」"
  },
  {
    "message": "大樹「いや？　全然、おっぱいが柔らかくてちょー気持ちいい」"
  },
  {
    "message": "紫衣「……相変わらずね」"
  },
  {
    "message": "大樹「はははっ……そういえば、この姿勢、ちょっと前を思い出すな」"
  },
  {
    "message": "紫衣「いつのことよ」"
  },
  {
    "message": "大樹「伊丹を裏切らないかって、お前持ちかけただろうが」"
  },
  {
    "message": "紫衣「……ああ、あったわね、そんな事」"
  },
  {
    "message": "大樹「お前の思惑通りになったなぁ……」"
  },
  {
    "message": "紫衣「あの時の思惑とは結構違う気もするけど……だって利用して捨てるつもりだったし」"
  },
  {
    "message": "大樹「酷い女だ……」"
  },
  {
    "message": "紫衣「状況が違うんだから、仕方ないでしょ」"
  },
  {
    "message": "大樹「そりゃそうだ」"
  },
  {
    "message": "紫衣「ホント……こんな事になるなんて、思いもしなかった」"
  },
  {
    "message": "大樹「同感だ……何がおきるかわからんもんだなぁ……」"
  },
  {
    "message": "紫衣「そうね……でも、振り返れば今日なんてドラマチックで面白かったわね」"
  },
  {
    "message": "大樹「おいおい……俺はもう二度と勘弁だ……特にアクション系は見る側で十分だよ」"
  },
  {
    "message": "紫衣「大丈夫、今度は私とのラブロマンスだけだから」"
  },
  {
    "message": "大樹「……じゃあ、すれ違いとかがあるのか？」"
  },
  {
    "message": "紫衣「ないわ、ひたすら愛し合うだけ」"
  },
  {
    "message": "大樹「それ……見る側は酷く退屈なんじゃないか？」"
  },
  {
    "message": "紫衣「見る側がつまんなくても、私達がよければ、それでいいのよ」"
  },
  {
    "message": "紫衣「……だから一緒に、周りが呆れるぐらい満足しましょ」"
  },
  {
    "message": "大樹（やれやれ）"
  },
  {
    "message": "こんな風にベタベタされたら、周りの人間はさぞ目のやり場に困る事だろう。"
  },
  {
    "message": "だが、それはあくまでも他人の話……"
  },
  {
    "message": "俺は俺と紫衣の満足を得るために……"
  },
  {
    "message": "どこの誰に見られようと……この先も、こうして口付けを交わし続けるだろう……"
  }
]